dissect/fve/__init__.py
dissect/fve/exceptions.py
dissect/fve/bde/__init__.py
dissect/fve/bde/bde.py
dissect/fve/bde/c_bde.py
dissect/fve/bde/eow.py
dissect/fve/bde/information.py
dissect/fve/bde/keys.py
dissect/fve/crypto/__init__.py
dissect/fve/crypto/_pycryptodome.py
dissect/fve/crypto/base.py
dissect/fve/crypto/elephant.py
dissect/fve/crypto/utils.py
dissect/fve/luks/__init__.py
dissect/fve/luks/af.py
dissect/fve/luks/c_luks.py
dissect/fve/luks/luks.py
dissect/fve/luks/metadata.py
dissect/fve/tools/__init__.py
dissect/fve/tools/dd.py
dissect_fve-4.4.dist-info/licenses/COPYRIGHT
dissect_fve-4.4.dist-info/licenses/LICENSE
dissect_fve-4.4.dist-info/METADATA
dissect_fve-4.4.dist-info/WHEEL
dissect_fve-4.4.dist-info/entry_points.txt
dissect_fve-4.4.dist-info/top_level.txt
dissect_fve-4.4.dist-info/RECORD
