Metadata-Version: 2.4
Name: dissect.fve
Version: 4.4
Summary: A Dissect module implementing a parsers for full volume encryption implementations, currently Linux Unified Key Setup (LUKS1 and LUKS2) and Microsoft's Bitlocker Disk Encryption
Author-email: Dissect Team <dissect@fox-it.com>
License-Expression: AGPL-3.0-or-later
Project-URL: homepage, https://dissect.tools
Project-URL: documentation, https://docs.dissect.tools/en/latest/projects/dissect.fve
Project-URL: repository, https://github.com/fox-it/dissect.fve
Classifier: Development Status :: 5 - Production/Stable
Classifier: Environment :: Console
Classifier: Intended Audience :: Developers
Classifier: Intended Audience :: Information Technology
Classifier: Operating System :: OS Independent
Classifier: Programming Language :: Python :: 3
Classifier: Topic :: Internet :: Log Analysis
Classifier: Topic :: Scientific/Engineering :: Information Analysis
Classifier: Topic :: Security
Classifier: Topic :: Utilities
Requires-Python: ~=3.9
License-File: LICENSE
License-File: COPYRIGHT
Requires-Dist: dissect.cstruct<5,>=4
Requires-Dist: dissect.util<4,>=3.22
Requires-Dist: pycryptodome
Requires-Dist: argon2-cffi
Provides-Extra: full
Requires-Dist: dissect.target; extra == "full"
Requires-Dist: rich; extra == "full"
Provides-Extra: dev
Requires-Dist: dissect.cstruct<5.0.dev,>=4.0.dev; extra == "dev"
Requires-Dist: dissect.util<4.0.dev,>=3.22.dev; extra == "dev"
Dynamic: license-file
